<?xml version="1.0" encoding="utf-8"?>
<usersdata><users><firstname>Priyanka</firstname><lastname>rao</lastname><usn>1JB15IS079</usn><email>priyankav.rao97@gmail.com</email><password>prer</password></users><users><firstname>Prerana</firstname><lastname>Harish</lastname><usn>1jb15is077</usn><email>preranaharishkumar@gmail.com</email><password>prer</password></users><users><firstname>abc</firstname><lastname>def</lastname><usn>1JB15IS079</usn><email>abc@gmail.com</email><password>up</password></users><users><firstname>shantanu</firstname><lastname>kumar</lastname><usn>123</usn><email>dsharishkumar@gmail.com</email><password>ihateyou</password></users></usersdata>
